{
    	"ARANDANO2":["Temporada", "Antiguedad", "Um", "Embalaje", "Material", "Codigo Embalaje", "Desc. Material", "Central", "Variedad", "Centro"
					, "Desc. Centro", "Productor", "Desc. Productor", "LOTE", "Fecha Recepcion", "PorcentajeExport", "Envase", "Cantidad Envase", "Kilos Partida", "Analisis Multiresiduos"
					, "Temp pulpa llegada", "Solidos Solubles", "Tratamiento", "Certificacion GGAP", "Precalibre", "Calibre XL", "Calibre J", "Calibre XJ", "Calibre XXJ"
					, "Pudricion u Hongo", "HeridasAbiertasPartiduras", "Fruta Blanda", "Machucon", "Deshidratacion", "Desgarro Pedicelar", "Exudacion", "Total condicion", "", "Heridas Cicatrizadas"
					, "Russet", "PolvoTierra", "Residuos Quimicos", "Manchas", "FaltaBloom", "Pedicelo", "Fruta Verde", "Fruta Roja", "PresenciaInsectos", "Total calidad"
					, "Total defectos", "AptitudViajeSegregacion", "CalificacionPartida", "Firm.prom", "ClasificacionAprRech", "inspeccion Proyeccion (peso muestra)", "TipoFrio", "Hora Revision","Aptitud de Viaje"],
					
	"DAGEN1": ["Temporada", "Antiguedad", "Um", "Embalaje", "Material", "Codigo Embalaje", "Desc. Material", "Central", "Variedad", "Centro"
					, "Desc. Centro", "Productor", "Desc. Productor", "LOTE", "Fecha Recepcion", "P.export.", "Envase", "Cantidad Envase", "Kilos Partida", "Analisis Multiresiduos"
					, "Temp pulpa llegada", "Solidos Solubles", "Tratamiento", "Certificacion GGAP", "Aptitud de Viaje", "Precalibre", "Calibre XL", "Calibre J", "Calibre XJ", "Calibre XXJ"
					, "Pudricion u Hongo", "Heridas Abiertas o Partiduras", "Fruta Blanda", "Machucon", "Deshidratacion", "Desgarro Pedicelar", "Exudacion", "Total condicion", "Pre-Calibre", "Heridas Cicatrizadas"
					, "Russet", "Polvo o Tierra", "Residuos Quimicos", "Manchas", "Falta de Bloom", "Pedicelo", "Fruta Verde", "Fruta Roja", "Presencia de Insectos", "Total calidad"
					, "Total defectos", "Aptitud de viaje segregacion", "Calificacion de la Partida", "Firm.prom", "Clasificacion (apr-Rech)", "inspeccion Proyeccion (peso muestra)", "Tipo de Frio", "Hora Revision"],
					
	"DAGEN2": ["Temporada", "Antiguedad", "Um", "Embalaje", "Material", "Codigo Embalaje", "Desc. Material", "Central", "Variedad", "Centro"
					, "Desc. Centro", "Productor", "Desc. Productor", "LOTE", "Fecha Recepcion", "P.export.", "Envase", "Cantidad Envase", "Kilos Partida", "Analisis Multiresiduos"
					, "Temp pulpa llegada", "Solidos Solubles", "Tratamiento", "Certificacion GGAP", "Aptitud de Viaje", "Precalibre", "Calibre 100", "Calibre 200", "Calibre 300", "Calibre 400"
					,"Presion Calibre Chico","Presion Calibre Grande","Presion Calibre Medio"
					,"Firmeza Maxima Mejilla 1 y 2","Firmeza Minima Mejillas 1 y 2","Firmeza Promedio Mejillas 1 y 2"
					,"Solidos Solubles Calibre Chico","Solidos Solubles Calibre Grande","Solidos Solubles Calibre Medio","Solidos Solubles Maximo","Solidos Solubles Minimo","Solidos Solubles Promedio"
					, "Pudricion u Hongo", "Heridas Abiertas o Partiduras", "Fruta Blanda", "Machucon", "Deshidratacion", "Desgarro Pedicelar", "Exudacion", "Total condicion", "Pre-Calibre", "Heridas Cicatrizadas"
					, "Russet", "Polvo o Tierra", "Residuos Quimicos", "Manchas", "Falta de Bloom", "Pedicelo", "Fruta Verde", "Fruta Roja", "Presencia de Insectos", "Total calidad"
					, "Total defectos", "Aptitud de viaje segregacion", "Calificacion de la Partida", "Firm.prom", "Clasificacion (apr-Rech)", "inspeccion Proyeccion (peso muestra", "Tipo de Frio", "Hora Revision",
					"Calificacion de Mercado"],
													
    "ARANDANO1OLD":["Temporada","Central ","ESPECIE","Descripcion Variedad","Temperatura °c","Peso Clamshell grs","Embalaje","Bolsa","Tipo Caja",
        "Base Pallets","GTIN","Codigo Embalaje","Fecha recepcion","","Lote","Cant-Cajas","Código productor","Productor","Calificacion Partida",
        "Aptitud de viaje segregacion ","Fruta Blanda %","Deshidratación %","Machucon %","Exudación","Heridas Abiertas","Desgarro Pedicilar",
        "Pudrición/Hongo (RECHAZO)","Presencia de Insectos (RECHAZO)","RESIDUOS (RECHAZO)","SUMA DEFECTOS DE CONDICION","Falta de Bloom(-33%)",
        "Russet","Heridas Cicatrizadas","Manchas","Fruta Roja(hasta 20% cubr.)","Fruta Verde","Fruta con pedicelo","Fruta con Polvo","Otros",
        "Descalibre","Suma de Defectos Calidad ","Total Defectos","Solidos Promedio","Nota de Calidad","Nota de Condicion" 
],
    "ARANDANO2OLD":[

"Temporada",
"Antiguedad",
"Um",
"Embalaje",
"Material",
"Codigo Embalaje",
"Desc. Material",
"Central ",
"Variedad",
"Centro",
"Desc. Centro",
"Productor",
"Desc. Productor",
"LOTE",
"Fecha Recepcion",
"P.export.",
"Envase",
"Cantidad Envase",
"Temp pulpa llegada","Kilos",
"Analisis Multiresiduos",
"Fecha De Recepcion","Hora Revision ",
"Cantidad Rejillas",
"Tipo de Frio",
"Solidos Solubles",
"Tratamiento",
"Certificacion GGAP",
"Aptitud de Viaje",
"Durofel Promedio",
"Machucon",
"Precalibre",
"Heridas Cicatrizadas",
"Russet",
"Polvo o Tierra",
"Residuos Quimicos",
"Deshidratacion",
"Manchas",
"Desgarro Pedicelar",
"Falta de Bloom",
"Exudacion",
"Pedicelo",
"Fruta Verde",
"Fruta Blanda",
"Fruta Roja",
"Pudricion u Hongo",
"Heridas Abiertas o Partiduras",
"Presencia de Insectos",
"Calibre L",
"Pre-Calibre",
"Calibre XL",
"Calibre J",
"Calibre XJ",
"Total condicion",
"Total calidad",
"Total Condicion",
"Total Calidad",
"Total defectos",
"Central",
"Cantidad Envases",
"Kilos",
"Aptitud de viaje segregacion",
"Calificacion de la Partida",
"Sol.s.pro",
"Firm.prom",
"Clasificacion (apr-Rech)",
"Cantidad Rejillas",
"Fecha De Recepcion",
"Estimado Exportable %",
"inspeccion Proyeccion (peso muestra)",
"(PC)    - 10mm",
"(L)     10 - 11,9 mm",
"(XL)    12 - 13,9 mm",
"(J)     14 - 15,9mm",
"(XJ)  16mm UP",
"Firmeza (10) Durofel",
"SUMA DEFECTOS DE CONDICION",
"Total Defectos",
"Suma de Defectos Calidad ",
"Brix (3)",
"Temp pulpa llegada",
"Hora Revision ",
"Presion Calibre Chico",
"Almidon Calibre Chico",
"Solidos Solubles Calibre Chico",
"Corazon Acuoso",
"Corazon Mohoso",
"Corazon Pardeamiento Int",
"Almidon Calbre Medio",
"Almidon Calibre Grande",
"Presion Calibre Grande",
"Presion Calibre Medio",
"Solidos Solubles Calibre Grande",
"Solidos Solubles Calibre Medio"
],
    "UVA1":[
"Temporada",
 "Centro",
 "Desc. Centro",
 "Material",
 "Desc. Material",
 "ESPECIE",
 "Variedad",
 "LOTE",
 "Productor",
 "Desc. Productor",
 "Fecha Produccion",
 "Antiguedad",
"Tipificacion",
"CALIBRE",
"CANTIDADRACIMOS",
"CATEGORIA",
"COD_CATEGORIA",
"COD_VARIEDAD",
"COLORNOTAINSPECCION",
"CUARTEL",
"Acuososidad",
"Antiguedad",
"Apariencia apertura (B-R-M)",
"Bajo Calibre",
"Bajopeso",
"Bayas Reventadas",
"Bayas con Partidura(Flame,magenta,superior)",
"Bayas con Partidura(otras)",
"Bayas con Pudricion",
"Bayas partiduras con Micelio",
"Bayas partiduras con Micelio(Sur)",
"Brix",
"Brix (3)",
"Caja Alta",
"Calificacion de la Partida",
"Centro",
"Clasificacion (apr-Rech)",
"Codigo Embalaje",
"Color",
"Color Escobajo",
"Compactos",
"Desgarro Pedicelar",
"Desgrane",
"Deshidratacion",
"Deshidratacion bayas",
"Deshidratacion de Laterales",
"Deshidratación Escobajo",
"Embaladora",
"Estimado Exportable %",
"Hombros Desganchados",
"Insectos Cuarentenarios",
"Matriz de Embalaje",
"Otro Defecto Calidad",
"Otro Defecto Condición",
"Peso Caja Neto",
"Quemado de Sol",
"Ralo(Paludo)",
"Residuos",
"Residuos Visuales",
"Rojas Falta Color",
"SIMPLIAPROBADO",
"Seleccion",
"Sobrecalibre",
"Sobrepeso",
"Solidos Solubles",
"Temporada",
"Verde Ambar y/o Amarillos",
"inspeccion Proyeccion (peso muestra)"

],
    "CAEREZA1":["Temporada","Centro","Desc. Centro","Material","Desc. Material","ESPECIE","Variedad","LOTE","Calibre","Proveedor","Desc. Productor",
"Um","Fec. Produccion","Aptitud de Viaje","Pudricion","Machucon","Deshidratacion","Pitting","Frutos Blandos","Heridas Abiertas","Partiduras","Media Luna","Mancha Parda",
"Dano Pajaro","Pedicelo Deshidratado","Frutos Dobles","Frutos Deformes","Russet","Sutura Severa","Heridas Cicatrizadas","Manchas","Sinpedicelo",
"Total def condicion","Total defec calidad","Total.defc","Pedicelo mal Cortado","Descalibre","Sol.s.pro","NOTADEFECTOCALIDAD","NOTADEFECTOCONDICION",
"Resultado inspeccion","Multiresiduos","Calidad","Calidad Etiquetado","Uso frío","Tipo Pallet","Desc. Origen","Pedicelo Deshidratado","Pedicelo mal Cortado"
]
   , 
    "CEREZA2":["Temporada","Centro","Desc. Centro","Material","Desc. Material","ESPECIE","Variedad","LOTE","Productor","Desc. Productor",
"Envase","Cantidad Envases","Kilos","Um","Fecha Recepcion","Antiguedad","P.export.","Analisis Multiresiduos",
"Tipo de Frio",
"Solidos Solubles",
"Tratamiento",
"Certificacion GGAP",
"Aptitud de Viaje",
"Durofel Promedio",
"Tipo de Packing",
"Sensibilidad a Partiduria",
"Presencia de Lobesia Botrana",
"Presencia de Escama",
"Presencia de Arana",
"Presencia de Chanchito Blanco",
"Presencia de Cydia Molesta",
"Fruta muy Blanda",
"Pudricion",
"Pudricion Seca",
"Machucon",
"Precalibre",
"Heridas Abiertas",
"Frutos Deformes",
"Heridas Cicatrizadas",
"Russet",
"Polvo o Tierra",
"Falta de Color",
"Residuos Quimicos",
"Golpe de Sol",
"Frutos Blandos",
"Partiduras",
"Varios Condicion",
"Mancha Trips",
"Fruto Deshidratado",
"Varios Calidad",
"Sin Pedicelo",
"Frutos Dobles",
"Sutura Severa",
"Pedicelo Deshidratado",
"Dano Pajaro",
"Pitting",
"Media Luna",
"Mancha Parda",
"Mancha Dorada",

"Calibre L",
"Calibre XL",
"Calibre J",
"Calibre 2J",
"Calibre 3J",
"Calibre 4J",
"Calibre 5J",

"Negro",
"Distribucion Negro",
"Rojo Claro",
"Distribucion Rojo Claro",
"Distribucion Falta de Color",
"Rojo Caoba",
"Distribucion Rojo Caoba",
"Rojo Caoba 3,3",
"Distribucion Rojo Caoba 3,3",
"Rojo Caoba 3,8",
"Distribucion Rojo Caoba 3,8",
"Rojo Santina",
"Distribucion Rojo Santina",
"Rojo",
"Distribucion Rojo",
"Rojo Caoba Oscuro",
"Distribucion Rojo Caoba Oscuro",


"Total Condicion",
"Total Calidad",
"Total defectos",
"Aptitud de viaje segregacion ",
"Calificacion de la Partida",
"Sol.s.pro",
"Firm.prom",
"Deshidratacion",
"Clasificacion (apr-Rech)",
"inspeccion Proyeccion (peso muestra)",

"Firmeza (10) Durofel",
"SUMA DEFECTOS DE CONDICION",
"Suma de Defectos Calidad ",
"Brix (3)",
"Temp pulpa llegada",
"Hora Revision ",
"Presion Calibre Chico",
"Almidon Calibre Chico",
"Solidos Solubles Calibre Chico",
"Corazon Acuoso",
"Corazon Mohoso",
"Corazon Pardeamiento Int",
"Almidon Calbre Medio",
"Almidon Calibre Grande",
"Presion Calibre Grande",
"Presion Calibre Medio",
"Solidos Solubles Calibre Grande",
"Solidos Solubles Calibre Medio"

]
   ,
    "CAROZO2":["Temporada","Centro","Desc. Centro","Material","Desc. Material","ESPECIE","Variedad","LOTE","Productor","Desc. Productor","Envase",
"Cantidad Envases","Kilos Partida","Um","Fecha Recepcion","PorcentajeExport","Tratamiento",
"Categoria Comercial",
"Calificacion de Mercado",
"Solidos Solubles Max",
"Solidos Solubles Min",
"Solidos Solubles Prom",
"Restriccion de Mercado",
"Presion Max Hombro",
"Presion Max Punta",
"Presion Max Quilla",
"Presion Min Hombro",
"Presion Min Mejilla 2",
"Presion Min Punta",
"Presion Min Quilla",
"Presion Prom Punta",
"Presion Prom Quilla",
"Presion Max Mejilla 1",
"Presion Max Mejilla 2",
"Presion Min Mejilla 1",
"Presion Prom Hombro",
"Presion Prom Mejilla 1",
"Presion Prom Mejilla 2",
"Pudricion",
"Machucon",
"Precalibre",
"Heridas Abiertas",
"Sobrecalibre",
"Frutos Deformes",
"Heridas Cicatrizadas",
"Russet",
"Polvo o Tierra",
"Residuos Quimicos",
"Golpe de Sol",
"Ramaleo",
"Frutos Blandos",
"Partiduras",
"Mancha Trips",
"Fruto Deshidratado",
"Sin Pedicelo",
"Desgarro Peduncular",
"Roce",
"Mancha Escama",
"Dano Granizo",
"Mancha",
"Pudricion Acida",
"Carozo Partido",
"Grietas",
"Puntas Blandas",
"Virosis",
"Craquelado",
"Color Burro",
"Hombros Blandos",
"Quilla Blandas",
"Frutos Bajo Color Cubrimiento",
"Caspocidad",
"Oidio",
"DanoPolilla",
"Incking",
"Fondo Verde",
"Sobremadurez",
"Sutura",
"Calibre Grande",
"Calibre Mediano",
"Calibre Chico",
"Color Fondo Verde",
"Dist Color Fondo Verde",
"Color Fondo Verde Virado",
"Dist Color Fondo Verde Virado",
"Color Fondo Amarillo",
"Dist Color Fondo Amarillo",
"ColorCubrimientoMenor40",
"DistColorCubrimientoMenor40",
"ColorCubrimiento40a70",
"DistColorCubrimiento40a70",
"ColorCubrimientoMayor70",
"DistColorCubrimientoMayor70",
"Total Condicion",
"Total Calidad",
"Total defectos",
"CalificacionPartida",
"Deshidratacion",
"Clasificacion (apr-Rech)",
"(PC)    - 10mm",
"SumaDefectosCondicion",
"Suma de Defectos Calidad ",
"Presion Calibre Chico",
"Almidon Calibre Chico",
"Solidos Solubles Calibre Chico",
"Corazon Acuoso",
"Corazon Mohoso",
"Corazon Pardeamiento Int",
"Almidon Calibre Medio",
"Almidon Calibre Grande",
"Presion Calibre Grande",
"Presion Calibre Medio",
"Solidos Solubles Calibre Grande",
"Solidos Solubles Calibre Medio"

]   ,
    "CAROZO1":["Temporada","Centro","Desc. Centro","Material","Desc. Material","ESPECIE","Variedad","LOTE","Calibre","Categoria","Proveedor",
"Desc. Productor","Stock Libre","Um","Fecha Produccion","Antiguedad","Pudricion Acida","Pudricion","Heridas Abiertas","Carozo Partido",
"Deshidratacion ","Partiduras","Grietas","Craquelado","Machucon ","Puntas Blandas","Hombro Blando","Quilla Blanda","Frutos Blandos","Roce",
"Desgarro Peduncular","Incking","Russet ","Golpe de Sol","Heridas Cicatrizadas","Falta de Color Cubrimiento","Color de Fondo Verde",
"Frutos Deformes","Ramaleo","Casposidad","Dano Granizo","Color Burro","Mancha","Mancha Trips","Mancha Escama","Virosis","Total.defc",
"Total def condicion","Total defec calidad","Descalibre","Desviación de calidad","PLU","Presion Prom","Solidos Solubles Promedio","Color de Fondo",
"NOTADEFECTOCALIDAD","NOTADEFECTOCONDICION","Resultado inspeccion","Multiresiduos","Restriccion de Mercado","Origen","F. cosecha","Altura Cabezal",
"T.envase","T. envase","P. envase","Calidad de Etiquetado","Uso frío","Tipo de Pallet"
],
    "MANZANA2":[  "Temporada",
 "Centro",
 "Desc. Centro",
 "Material",
 "Desc. Material",
 "ESPECIE",
 "Variedad",
 "LOTE",
 "Productor",
 "Desc. Productor",
 "Envases",
 
"Kilos",
 "Um",
 "Fecha Recepcion",
 "Antiguedad",
 "P.export.",
 "Categoria Comercial",
"Categoria Choice",
"Categoria Fancy",
"Categoria Cat2",
"Categoria Cat1",
"Categoria Extra Fancy A",
"Categoria Extra Fancy",
"Categoria Premium",
"Categoria Super",
"Certificacion GGAP",
"Presencia de Plagas ",
"Analisis Multiresiduos",
"Tipo de Tratamiento",
"Tamano de Partida",
"Camara",
"Tipificacion",
"Tipo de Frio",
"Falta de Color Cubrimiento",
"Varios Condicion",
"Sunscald",
"Escalado",
"Deshidratacion",
"Quemadura de sol",
"Machucon Severo",
"Machucon Moderado",
"Infiltracion Acuosa",
"Bitter Pit",
"Cracking",
"Partidura Peduncular",
"Mancha Lenticelar",
"Golpe de Sol Severo",
"Pudricion",
"Sobre Madurez",
"Pedunculo Desgarrado",
"Heridas Abiertas",
"Insecto Vivo",
"Sobrecalibre",
"Precalibre",
"Varios Calidad",
"Corcho Severo",
"Checking Severo",
"Coloracion Rojiza",
"Coloracion Blanca",
"Frutos Deformes",
"Mancha por Roce",
"Venturia",
"Russet Peduncular Severo",
"Mancha Severa",
"Dano por Granizo Severo",
"Russet Grave",
"Dano Insecto",
"Dano por Helada",
"Ramaleo",
"Sobre Calibre",
"Calibre Grande",
"Calibre Mediano",
"Calibre Chico",
"Pre-Calibre",
"Cantidad Frutos Calibre 100",
"Total Condicion",
"Total Calidad",
"Total defectos",
"Calificacion de la Partida",
"Clasificacion (apr-Rech)",
"inspeccion Proyeccion (peso muestra)",
"(PC)    - 10mm",
"SUMA DEFECTOS DE CONDICION",
"Suma de Defectos Calidad ",
"Temp pulpa llegada",
"Hora Revision ",


"Presion Calibre Grande",
"Presion Calibre Medio",
"Presion Calibre Chico",

"Almidon Calibre Grande",
"Almidon Calbre Medio",
"Almidon Calibre Chico",

"Corazon Acuoso",
"Corazon Mohoso",
"Corazon Pardeamiento Int",

"Solidos Solubles Calibre Grande",
"Solidos Solubles Calibre Medio",
"Solidos Solubles Calibre Chico"


],
"MANZANA1":[  "Temporada",
 "Centro",
 "Material",
 "Desc. Material",
 "ESPECIE",
 "Variedad",
 "LOTE",
 "Productor",
 "Desc. Productor",
"CALIBRE",
"CATEGORIA",
"COD_CATEGORIA",
"COD_VARIEDAD",

"GTIN",
"GGN",
"Tipo de Pallet",
"Altura Cabezal",
"Firmeza Promedio",
"PLU",
"Tipo de Caja",
"Calidad de Etiquetado",
"Materiales de Embalaje",
"Tipo Bolsa",
"Descalibrado",
"Golpe de Sol Sevro",
"Varios Condicion",
"Deshidratacion Severa",
"Quemadura de Sol",
"Machucon Severo",
"Escaldado",
"Sunscald",
"Bitter Pit",
"Pudricion",
"Lenticelosis",
"Dano Insecto",
"Cracking",
"Partiduras",
"Pedunculo Desgarrado",
"Heridas Abiertas",
"Sobre Madurez",
"Presencia de Plagas",
"Desviacion de Calidad",
"Corcho Severo",
"Venturia",
"Color Pardo",
"Frutos Deformes",
"Falta de Color Cubrimiento",
"Heridas Cicatrizadas",
"Polvo o Tierra",
"Russet Grave",
"Russert Peduncular Severo",
"Mancha por Roce",
"P.export.",
"Envase",
"Cantidad Envase",
"Total condicion",
"Total calidad",
"Total Condicion",
"Total Calidad",
"Total defectos",

"Calificacion de la Partida",
"PESOTOTALMUESTRA",
"PESOBRUTOMUESTRA",
"PESOTARAMUESTRA",
"Hora Revision"

],

"CEREZA1":[  "Temporada",
 "Centro",
 "Desc. Centro",
 "Material",
 "Desc. Material",
 "Especie",
 "Variedad",
 "LOTE",
 "Productor",
 "Desc. Productor",
 "Envase",
 "Cantidad Envases",
 "Stock Libre",
 "Stock Sin Inspeccion",
 "Stock Bloqueado",
 "Um",
 "Fecha Recepcion",
 "Pedicelo Deshidratado","Pedicelo mal Cortado"
 
],
"KIWI2":[  "Temporada",
 "Centro",
 "Desc. Centro",
 "Material",
 "Desc. Material",
 "Especie",
 "Variedad",
 "LOTE",
 "Productor",
 "Desc. Productor",
 "Envase",
 "Cantidad Envases",
 "Stock Libre",
 "Stock Sin Inspeccion",
 "Stock Bloqueado",
 "Um",
"Kilos Partida",
 "Fecha Recepcion",
 "P.export.",
 "Certificacion",
"Restriccion de Mercado",
"Presencia de Plagas ",
"Analisis Multiresiduos",
"Aptitud de Viaje",
"Categoria Cat1",
"Categoria Cat2",
"Categoria Comercial",
"Categoria Premium",
"Machucon Severo",
"Deshidratacion",
"Heridas Abiertas",
"Frutos Blandos",
"Pudricion",
"Precalibre",
"Mancha de Fumagina",
"Polvo o Tierra",
"Frutos Abanico",
"Frutos Dobles",
"Frutos Planos",
"Dano Eulia",
"Quemadura de Sol",
"Mancha de Agua Severa",
"Heridas Cicatrizadas",
"Frutos Deformes",
"Golpe de Sol Severo",
"Russet Grave",
"Hombro Caido Severo",
"Marca Hayward Severa",
"Frutos con Pedunculos",
"Sobre Calibre",
"Calibre Grande",
"Calibre Mediano",
"Calibre Chico",
"Pre-Calibre",
"Antiguedad",
"Total Condicion",
"Total Calidad",
"Total defectos",
"Central",
"Kilos",
"Aptitud de viaje segregacion ",
"Calificacion de la Partida",
"Sol.s.pro",
"Firmeza Promedio",
"Clasificacion (apr-Rech)",
"inspeccion Proyeccion (peso muestra)",
"(PC)    - 10mm",
"SUMA DEFECTOS DE CONDICION",
"Suma de Defectos Calidad ",
"Temp pulpa llegada",
"Hora Revision ",
"Solidos Solubles Maximo",
"Solidos Solubles Minimo",
"Solidos Solubles Promedio",
"Presion Promedio",
"Presion Maxima",
"Presion Minima",
"Camara",
"Tipificacion",
"Tipo de Frio"

 
],
"PERA2":[
    "Temporada",
    "Centro",
    "Desc. Centro",
    "Material",
    "Desc. Material",
    "ESPECIE",
    "Variedad",
    "LOTE",
    "Productor",
    "Calificacion de la Partida",
    "Desc. Productor",
    "Fecha Recepcion",
    "P.export.",
    "Antiguedad",
    "Kilos Partida",
    "Camara",
    "Tipificacion",
    "Categoria Cat1",
    "Categoria Cat2",
    "Categoria Premium",
    "Categoria XFCY",
    "Categoria FCY",
    "Categoria Comercial",
    "Color de Fondo Verde",
    "Color de Fondo Verde Crema",
    "Color de Fondo Crema",
    "Color de Fondo Amarillo",
    "Color Cubrimiento ",
    "Presion Maximo Calibre Chico",
    "Presion Minima Calibre Chico",
    "Presion Promedio Calibre chico",
    "Presion Maxima Calibre Grande",
    "Presion Minima Calibre Grande",
    "Presion Promedio Calibre Grande",
    "Presion Maxima Calibre Mediano",
    "Presion Minima Calibre Mediano",
    "Presion Promedio Calibre Media",
    "Solidos Maximo Calibre Grande",
    "Solidos Minimo Calibre Grande",
    "Solidos Promedio Calibre Grande",
    "Solidos Maximo Calibre Mediano",
    "Solidos Minimo Calibre Mediano",
    "Solidos Promedio Calibre Mediano",
    "Solidos Maximo Calibre Chico",
    "Solidos Minimo Calibre Chico",
    "Solidos Promedio Calibre Chico",
    "Calificacion de Mercado",
    "Tipo de Frio",
    "Tratamiento",
    "Presencia de Plagas",
    "Analisis Multiresiduos",
    "Tipo de Packing",
    "Otros Defectos de Condicion",
    "Otros Defectos de Calidad",
    "Sobrecalibre",
    "Precalibre",
    "Deshidratacion",
    "Russet",
    "Heridas Abiertas",
    "Heridas Cicatrizadas",
    "Sobre Madurez",
    "Dano Granizo",
    "Pudricion",
    "Dano Insecto",
    "Roce",
    "Golpe de Sol",
    "Desgarro Peduncular",
    "Quemadra de Sol",
    "Machucon",
    "Coloracion Rojiza",
    "Stony Pit",
    "Litiasis",
    "Frutos Deformes",
    "Falta Color Cubrimiento",
    "Mancha",
    "Mancha Escama",
    "Ramaleo",
    "Corcho",
    "Venturia",
    "Sobre Calibre",
    "Calibre Grande",
    "Calibre Mediano",
    "Calibre Chico",
    "Pre-Calibre",
    "Um",
    "Envase",
    "Cantidad Envases",
    "totalKilosPartida",
    "Total Condicion",
    "Total Calidad",
    "Total defectos"
   

],
"PERA1":[
    "Temporada",
    "Centro",
    "Desc. Centro",
    "Material",
    "Desc. Material",
    "ESPECIE",
    "Variedad",
    "LOTE",
    "Productor",
    "Calificacion de la Partida",
    "Desc. Productor",
    "Fecha Produccion",
    "Antiguedad",
    "Camara",
    "Tipificacion",
    "Categoria Cat 1",
    "Categoria Cat 2",
    "Categoria Premium",
    "Categoria Comercial",
    "Color de Fondo Verde",
    "Color de Fondo Verde Crema",
    "Color de Fondo Crema",
    "Color de Fondo Amarillo",
    "Color Cubrimiento ",
    "Presion Maximo Calibre Chico",
    "Presion Minima Calibre Chico",
    "Presion Promedio Calibre chico",
    "Presion Maxima Calibre Grande",
    "Presion Minima Calibre Grande",
    "Presion Promedio Calibre Grande",
    "Presion Maxima Calibre Mediano",
    "Presion Minima Calibre Mediano",
    "Presion Promedio Calibre Media",
    "Solidos Maximo Calibre Grande",
    "Solidos Minimo Calibre Grande",
    "Solidos Promedio Calibre Grande",
    "Solidos Maximo Calibre Mediano",
    "Solidos Minimo Calibre Mediano",
    "Solidos Promedio Calibre Mediano",
    "Solidos Maximo Calibre Chico",
    "Solidos Minimo Calibre Chico",
    "Solidos Promedio Calibre Chico",
    "Calificacion de Mercado",
    "Tipo de Frio",
    "Tratamiento",
    "Presencia de Plagas",
    "Analisis Multiresiduos",
    "Tipo de Packing",
    "Otros Defectos de Condicion",
    "Otros Defectos de Calidad",
    "Sobrecalibre",
    "Precalibre",
    "Deshidratacion",
    "Russet",
    "Heridas Abiertas",
    "Heridas Cicatrizadas",
    "Sobre Madurez",
    "Dano Granizo",
    "Pudricion",
    "Dano Insecto",
    "Roce",
    "Golpe de Sol",
    "Desgarro Peduncular",
    "Quemadra de Sol",
    "Machucon",
    "Coloracion Rojiza",
    "Stony Pit",
    "Litiasis",
    "Frutos Deformes",
    "Falta Color Cubrimiento",
    "Mancha",
    "Mancha Escama",
    "Ramaleo",
    "Corcho",
    "Venturia",
    "Sobre Calibre",
    "Calibre Grande",
    "Calibre Mediano",
    "Calibre Chico",
    "Pre-Calibre",
    "Color Verde",
    "Distribucion Color Verde",
    "Color Verde Crema",
    "Distribucion Color Verde Crema",
    "Color Crema ",
    "Distribucion Color Crema ",
    "Color Amarillo",
    "Distribucion Color Amarillo",
    "Color de Cubrimiento",
    "Distribucion Color de Cubrimiento",
    "totalKilosPartida",
    "Temporada",
    "Antiguedad",
    "Um",
    "Embalaje",
    "Material",
    "Codigo Embalaje",
    "Desc. Material",
    "Descripcion Embalaje o codigo",
    "Central ",
    "Descripcion Variedad",
    "Variedad",
    "Centro",
    "Desc. Centro",
    "Productor",
    "Desc. Productor",
    "Descripcion Productor",
    "Fecha Recepcion",
    "P.export.",
    "Envase",
    "Cantidad Envase",
    "Total condicion",
    "Total calidad",
    "Total Condicion",
    "Total Calidad",
    "Total defectos",
    "Central",
    "Cantidad Envases",
    "Kilos",
    "Calificacion de la Partida",
    "Sol.s.pro",
    "Firm.prom",
    "Clasificacion (apr-Rech)",
    "inspeccion Proyeccion (peso muestra)",
    "(PC)    - 10mm",
    "SUMA DEFECTOS DE CONDICION",
    "Total Defectos",
    "Suma de Defectos Calidad ",
    "Temp pulpa llegada",
    "Hora Revision ",
    "Presion Calibre Chico",
    "Almidon Calibre Chico",
    "Solidos Solubles Calibre Chico",
    "Corazon Acuoso",
    "Corazon Mohoso",
    "Corazon Pardeamiento Int",
    "Almidon Calbre Medio",
    "Almidon Calibre Grande",
    "Presion Calibre Grande",
    "Presion Calibre Medio",
    "Solidos Solubles Calibre Grande",
    "Solidos Solubles Calibre Medio",
    "Descalibre"

]
            
}

